README.md
setup.py
ruqqus/__init__.py
ruqqus_api.egg-info/PKG-INFO
ruqqus_api.egg-info/SOURCES.txt
ruqqus_api.egg-info/dependency_links.txt
ruqqus_api.egg-info/not-zip-safe
ruqqus_api.egg-info/requires.txt
ruqqus_api.egg-info/top_level.txt