Metadata-Version: 2.1
Name: ruqqus-api
Version: 0.4.1
Summary: Unofficial Ruqqus API Wrapper
Home-page: https://github.com/AgeOfMarcus/ruqqus-api
Author: AgeOfMarcus
Author-email: marcus@marcusweinberger.com
License: UNKNOWN
Platform: UNKNOWN
